odoo/addons/hr_expense_tax_adjust/README.rst
odoo/addons/hr_expense_tax_adjust/__init__.py
odoo/addons/hr_expense_tax_adjust/__manifest__.py
odoo/addons/hr_expense_tax_adjust/i18n/hr_expense_tax_adjust.pot
odoo/addons/hr_expense_tax_adjust/i18n/it.po
odoo/addons/hr_expense_tax_adjust/models/__init__.py
odoo/addons/hr_expense_tax_adjust/models/hr_expense.py
odoo/addons/hr_expense_tax_adjust/readme/CONTRIBUTORS.rst
odoo/addons/hr_expense_tax_adjust/readme/DESCRIPTION.rst
odoo/addons/hr_expense_tax_adjust/static/description/icon.png
odoo/addons/hr_expense_tax_adjust/static/description/index.html
odoo/addons/hr_expense_tax_adjust/static/src/js/tax_group.js
odoo/addons/hr_expense_tax_adjust/static/src/xml/tax_group.xml
odoo/addons/hr_expense_tax_adjust/views/asset_backend.xml
odoo/addons/hr_expense_tax_adjust/views/hr_expense_views.xml
odoo14_addon_hr_expense_tax_adjust-14.0.1.0.1.dev5.dist-info/METADATA
odoo14_addon_hr_expense_tax_adjust-14.0.1.0.1.dev5.dist-info/WHEEL
odoo14_addon_hr_expense_tax_adjust-14.0.1.0.1.dev5.dist-info/top_level.txt
odoo14_addon_hr_expense_tax_adjust-14.0.1.0.1.dev5.dist-info/RECORD
